adafri/__init__.py
adafri/utils/__init__.py
adafri/utils/country.py
adafri/utils/phone_number.py
adafri/utils/pick.py
adafri/utils/pick2.py
adafri/utils/response.py
adafri/utils/utils.py
adafri/v1/__init__.py
adafri/v1/account/__init__.py
adafri/v1/account/models/__init__.py
adafri/v1/account/models/account.py
adafri/v1/account/models/account_fields.py
adafri/v1/auth/__init__.py
adafri/v1/auth/firebase_auth/__init__.py
adafri/v1/auth/firebase_auth/firebase_auth.py
adafri/v1/auth/models/__init__.py
adafri/v1/auth/oauth/__init__.py
adafri/v1/auth/oauth/token_debug.py
adafri/v1/auth/oauth/models/__init__.py
adafri/v1/auth/oauth/models/client.py
adafri/v1/auth/oauth/models/client_fields.py
adafri/v1/auth/oauth/models/code.py
adafri/v1/auth/oauth/models/code_fields.py
adafri/v1/auth/oauth/models/grant.py
adafri/v1/auth/oauth/models/grant_fields.py
adafri/v1/auth/oauth/models/token.py
adafri/v1/auth/oauth/models/token_fields.py
adafri/v1/auth/oauth/server/__init__.py
adafri/v1/auth/oauth/server/oidc_server.py
adafri/v1/auth/oauth/server/server.py
adafri/v1/base/__init__.py
adafri/v1/base/firebase_collection.py
adafri/v1/gads/__init__.py
adafri/v1/gads/utils.py
adafri/v1/gads/data/__init__.py
adafri/v1/gads/data/adsChannel.py
adafri/v1/gads/data/adschedules.py
adafri/v1/gads/data/bids.py
adafri/v1/gads/data/demographics.py
adafri/v1/gads/data/devices.py
adafri/v1/gads/data/objectives.py
adafri/v1/gads/display/__init__.py
adafri/v1/gads/display/adgroups/__init__.py
adafri/v1/gads/display/adgroups/adgroup.py
adafri/v1/gads/display/adgroups/adgroup_fields.py
adafri/v1/gads/display/models/__init__.py
adafri/v1/gads/display/models/display.py
adafri/v1/gads/display/models/display_fields.py
adafri/v1/gads/models/__init__.py
adafri/v1/gads/models/adchannel.py
adafri/v1/gads/models/adschedules.py
adafri/v1/gads/models/ages.py
adafri/v1/gads/models/base.py
adafri/v1/gads/models/base_adgroup_fields.py
adafri/v1/gads/models/base_campaign_fields.py
adafri-2.0.6.dist-info/METADATA
adafri-2.0.6.dist-info/WHEEL
adafri-2.0.6.dist-info/top_level.txt
adafri-2.0.6.dist-info/RECORD
