Metadata-Version: 2.2
Name: adafri
Version: 2.0.6
Summary: Adafri python module
Author: Ibrahima Touré
Author-email: ibrahima.toure.dev@gmail.com
Dynamic: author
Dynamic: author-email
Dynamic: description
Dynamic: summary
